README.md
setup.py
libpythonph/__init__.py
libpythonph/git_hubapi.py
libpythonph.egg-info/PKG-INFO
libpythonph.egg-info/SOURCES.txt
libpythonph.egg-info/dependency_links.txt
libpythonph.egg-info/not-zip-safe
libpythonph.egg-info/requires.txt
libpythonph.egg-info/top_level.txt