Metadata-Version: 2.1
Name: libpythonph
Version: 0.1
Summary: Módulo de Estudo de ferramentas de desenvolvimento em Python
Home-page: https://github.com/pedromadureira000/pytools
Author: Pedro Henrique Madureira
Author-email: pedromadureira000@gmail.com
License: GNU AFFERO GENERAL PUBLIC LICENSE
Platform: UNKNOWN
Classifier: Development Status :: 2 - Pre-Alpha
Classifier: Environment :: Console
Classifier: Intended Audience :: Developers
Classifier: License :: OSI Approved :: GNU Affero General Public License v3 or later (AGPLv3+)
Classifier: Operating System :: OS Independent
Classifier: Programming Language :: Python
Classifier: Programming Language :: Python :: 3.6
Classifier: Framework :: Pytest
